MANIFEST.in
README.txt
bootstrap.py
buildout.cfg
setup.py
versions.cfg
docs/HISTORY.txt
src/affinitic/__init__.py
src/affinitic.caching.egg-info/PKG-INFO
src/affinitic.caching.egg-info/SOURCES.txt
src/affinitic.caching.egg-info/dependency_links.txt
src/affinitic.caching.egg-info/namespace_packages.txt
src/affinitic.caching.egg-info/not-zip-safe
src/affinitic.caching.egg-info/requires.txt
src/affinitic.caching.egg-info/top_level.txt
src/affinitic/caching/__init__.py
src/affinitic/caching/configure.zcml
src/affinitic/caching/interfaces.py
src/affinitic/caching/memcached.py
src/affinitic/caching/memcached.txt
src/affinitic/caching/memcached_usage.pt
src/affinitic/caching/memcached_usage_view.py
src/affinitic/caching/memoize.py
src/affinitic/caching/overrides.zcml
src/affinitic/caching/testing.py
src/affinitic/caching/testing.zcml
src/affinitic/caching/views.zcml
src/affinitic/caching/tests/__init__.py
src/affinitic/caching/tests/test_memcached.py
src/affinitic/caching/tests/test_memoize.py