Metadata-Version: 1.1
Name: affinitic.caching
Version: 0.7.1
Summary: Caching function for affinitic projects
Home-page: http://svn.plone.org/svn/collective/
Author: Jean-Francois Roche
Author-email: jfroche@affinitic.be
License: GPL
Keywords: caching memcached
Platform: UNKNOWN
Classifier: Programming Language :: Python
